AUTHORS
COPYING
MANIFEST.in
NEWS
README
TODO
setup.py
awescript/awescript.py
bin/_preamble.py
bin/preprardir.py
bin/pyrescene.py
bin/retag.py
bin/srr.py
bin/srr_extract_srs.py
bin/srr_merge.py
bin/srr_sort.py
bin/srs.py
bin/srs_bad.py
bin/srs_batch.py
bin/srs_size.py
bin/py2exe/auto.bat
bin/py2exe/shell_extension-setup.bat
bin/py2exe/shell_extension-srrit.bat
bin/windows/add_current_dir_to_path.bat
bin/windows/ashellextension_setup.bat
bin/windows/ashellextension_srrit.bat
bin/windows/best.bat
bin/windows/preprardir.bat
bin/windows/pyrescene.bat
bin/windows/pysrr.bat
bin/windows/pysrs.bat
bin/windows/rerar.bat
bin/windows/retag.bat
bin/windows/srr_extract.bat
bin/windows/srr_extract_srs.bat
bin/windows/srr_merge.bat
bin/windows/srr_sort.bat
bin/windows/srs_bad.bat
bin/windows/srs_size.bat
bin/windows/vs.bat
pyReScene.egg-info/PKG-INFO
pyReScene.egg-info/SOURCES.txt
pyReScene.egg-info/dependency_links.txt
pyReScene.egg-info/top_level.txt
rerar/rar.py
rerar/rarfile.py
rerar/rerar.py
resample/__init__.py
resample/asf.py
resample/ebml.py
resample/flac.py
resample/fpcalc.py
resample/m2ts.py
resample/main.py
resample/mov.py
resample/mp3.py
resample/riff.py
resample/srs.py
resample/stream.py
rescene/__init__.py
rescene/crc32combine.py
rescene/main.py
rescene/ordereddict.py
rescene/osohash.py
rescene/rar.py
rescene/rarstream.py
rescene/srr.py
rescene/unrar.py
rescene/utility.py
usenet/_yenc.so
usenet/nzb_age.py
usenet/nzb_merge.py
usenet/nzb_rename.py
usenet/nzb_sample_extract.py
usenet/nzb_split.py
usenet/nzb_ue.py
usenet/nzb_utils.py
usenet/srr_usenet.py
usenet/srr_usenet_template.cfg
usenet/yenc.py
usenet/pynzb/__init__.py
usenet/pynzb/base.py
usenet/pynzb/etree_nzb.py
usenet/pynzb/expat_nzb.py
usenet/pynzb/lxml_nzb.py
usenet/pynzb/tests.py