Metadata-Version: 1.1
Name: pyReScene
Version: 0.7
Summary: Backup and restore scene release metadata
Home-page: https://bitbucket.org/Gfy/pyrescene
Author: Gfy
Author-email: pyrescene@gmail.com
License: MIT
Download-URL: https://bitbucket.org/Gfy/pyrescene/downloads/pyReScene-0.7.zip
Keywords: rescene,srr,resample,srs,repackage,rar,avi,mkv,mp4,wmv,warez,scene,compressed,mp3,flac,retag
Platform: UNKNOWN
Classifier: Development Status :: 5 - Production/Stable
Classifier: Programming Language :: Python :: 2.6
Classifier: Programming Language :: Python :: 2.7
Classifier: Programming Language :: Python :: 3.2
Classifier: Programming Language :: Python :: 3.3
Classifier: Programming Language :: Python :: 3.4
Classifier: Environment :: Console
Classifier: Intended Audience :: End Users/Desktop
Classifier: Intended Audience :: Developers
Classifier: License :: OSI Approved :: MIT License
Classifier: Natural Language :: English
Classifier: Operating System :: OS Independent
Classifier: Topic :: System :: Archiving :: Backup
Classifier: Topic :: Sociology :: History
Classifier: Topic :: Utilities
